<Properties StartupConfiguration="{BECC6228-17AD-4414-A29A-DCDC583B1793}|Default">
  <MonoDevelop.Ide.Workbench ActiveDocument="api/Program.cs">
    <Files>
      <File FileName="Servicios/Implem/TipoEventoServicio.cs" Line="19" Column="21" />
      <File FileName="Servicios/Implem/DetalleEstadisticaServicio.cs" Line="21" Column="57" />
      <File FileName="Servicios/Contracts/IDetalleEstadisticaPorEnlaceServicio.cs" Line="11" Column="9" />
      <File FileName="Servicios/Contracts/IDetalleEstadisticaServicio.cs" Line="12" Column="88" />
      <File FileName="api/Controllers/DetalleEstadisticaController.cs" Line="8" Column="32" />
      <File FileName="api/Program.cs" Line="62" Column="27" />
      <File FileName="api/Extensions/ServiceExtensions.cs" Line="37" Column="10" />
    </Files>
    <Pads>
      <Pad Id="ProjectPad">
        <State name="__root__">
          <Node name="ProyectoGestelWeb2022" expanded="True" selected="True" />
        </State>
      </Pad>
      <Pad Id="MonoDevelop.Debugger.WatchPad">
        <State>
          <Value>StackTrace</Value>
        </State>
      </Pad>
    </Pads>
  </MonoDevelop.Ide.Workbench>
  <MultiItemStartupConfigurations />
  <MonoDevelop.Ide.DebuggingService.Breakpoints>
    <BreakpointStore />
  </MonoDevelop.Ide.DebuggingService.Breakpoints>
  <MonoDevelop.Ide.DebuggingService.PinnedWatches />
  <MonoDevelop.Ide.Workspace ActiveConfiguration="Debug" />
  <Debugger.DebugSourceFolders />
  <MonoDevelop.Ide.ItemProperties.api PreferredExecutionTarget="/Applications/Google Chrome.app" />
</Properties>